openobserve/__init__.py
openobserve/exceptions.py
openobserve/flusher.py
openobserve/handler.py
openobserve/logger.py
openobserve/sender.py
tests/__init__.py
tests/test_add_context.py
tests/test_extra_fields.py
tests/test_openobserveHandler.py
tests/test_openobserveSender.py
tests/mockOpenObserveListener/__init__.py
tests/mockOpenObserveListener/listener.py
tests/mockOpenObserveListener/logsList.py
tests/mockOpenObserveListener/persistentFlags.py
openobserve_python_handler-1.0.3.dist-info/LICENSE
openobserve_python_handler-1.0.3.dist-info/METADATA
openobserve_python_handler-1.0.3.dist-info/WHEEL
openobserve_python_handler-1.0.3.dist-info/top_level.txt
openobserve_python_handler-1.0.3.dist-info/RECORD
